flask_ckeditor/__init__.py
flask_ckeditor/fields.py
flask_ckeditor/utils.py
flask_ckeditor/static/basic/CHANGES.md
flask_ckeditor/static/basic/LICENSE.md
flask_ckeditor/static/basic/README.md
flask_ckeditor/static/basic/build-config.js
flask_ckeditor/static/basic/ckeditor.js
flask_ckeditor/static/basic/config.js
flask_ckeditor/static/basic/contents.css
flask_ckeditor/static/basic/styles.js
flask_ckeditor/static/basic/adapters/jquery.js
flask_ckeditor/static/basic/lang/af.js
flask_ckeditor/static/basic/lang/ar.js
flask_ckeditor/static/basic/lang/az.js
flask_ckeditor/static/basic/lang/bg.js
flask_ckeditor/static/basic/lang/bn.js
flask_ckeditor/static/basic/lang/bs.js
flask_ckeditor/static/basic/lang/ca.js
flask_ckeditor/static/basic/lang/cs.js
flask_ckeditor/static/basic/lang/cy.js
flask_ckeditor/static/basic/lang/da.js
flask_ckeditor/static/basic/lang/de-ch.js
flask_ckeditor/static/basic/lang/de.js
flask_ckeditor/static/basic/lang/el.js
flask_ckeditor/static/basic/lang/en-au.js
flask_ckeditor/static/basic/lang/en-ca.js
flask_ckeditor/static/basic/lang/en-gb.js
flask_ckeditor/static/basic/lang/en.js
flask_ckeditor/static/basic/lang/eo.js
flask_ckeditor/static/basic/lang/es-mx.js
flask_ckeditor/static/basic/lang/es.js
flask_ckeditor/static/basic/lang/et.js
flask_ckeditor/static/basic/lang/eu.js
flask_ckeditor/static/basic/lang/fa.js
flask_ckeditor/static/basic/lang/fi.js
flask_ckeditor/static/basic/lang/fo.js
flask_ckeditor/static/basic/lang/fr-ca.js
flask_ckeditor/static/basic/lang/fr.js
flask_ckeditor/static/basic/lang/gl.js
flask_ckeditor/static/basic/lang/gu.js
flask_ckeditor/static/basic/lang/he.js
flask_ckeditor/static/basic/lang/hi.js
flask_ckeditor/static/basic/lang/hr.js
flask_ckeditor/static/basic/lang/hu.js
flask_ckeditor/static/basic/lang/id.js
flask_ckeditor/static/basic/lang/is.js
flask_ckeditor/static/basic/lang/it.js
flask_ckeditor/static/basic/lang/ja.js
flask_ckeditor/static/basic/lang/ka.js
flask_ckeditor/static/basic/lang/km.js
Flask_CKEditor-1.0.0.dist-info/LICENSE
Flask_CKEditor-1.0.0.dist-info/METADATA
Flask_CKEditor-1.0.0.dist-info/WHEEL
Flask_CKEditor-1.0.0.dist-info/top_level.txt
Flask_CKEditor-1.0.0.dist-info/RECORD
