Metadata-Version: 2.1
Name: Flask-CKEditor
Version: 1.0.0
Summary: CKEditor integration for Flask.
Home-page: http://github.com/helloflask/flask-ckeditor
Author: Grey Li
Author-email: withlihui@gmail.com
License: MIT
Platform: any
Classifier: Environment :: Web Environment
Classifier: Intended Audience :: Developers
Classifier: License :: OSI Approved :: MIT License
Classifier: Operating System :: OS Independent
Classifier: Programming Language :: Python
Classifier: Programming Language :: Python :: 3
Classifier: Programming Language :: Python :: 3.8
Classifier: Programming Language :: Python :: 3.9
Classifier: Programming Language :: Python :: 3.10
Classifier: Programming Language :: Python :: 3.11
Classifier: Programming Language :: Python :: 3.12
Classifier: Topic :: Internet :: WWW/HTTP :: Dynamic Content
Classifier: Topic :: Software Development :: Libraries :: Python Modules
License-File: LICENSE
Requires-Dist: Flask
Provides-Extra: all
Requires-Dist: flask-wtf; extra == "all"
Requires-Dist: bleach; extra == "all"
